opensesame_plugins/experiment_manager/__init__.py
opensesame_plugins/experiment_manager/experiment_manager/__init__.py
opensesame_plugins/experiment_manager/experiment_manager/experiment_manager.png
opensesame_plugins/experiment_manager/experiment_manager/experiment_manager.py
opensesame_plugins/experiment_manager/experiment_manager/experiment_manager_large.png
opensesame_plugin_experiment_manager-3.2.0.dist-info/COPYING
opensesame_plugin_experiment_manager-3.2.0.dist-info/LICENSE.md
opensesame_plugin_experiment_manager-3.2.0.dist-info/METADATA
opensesame_plugin_experiment_manager-3.2.0.dist-info/WHEEL
opensesame_plugin_experiment_manager-3.2.0.dist-info/RECORD
