Metadata-Version: 2.3
Name: opensesame-plugin-experiment_manager
Version: 3.2.0
Summary: An OpenSesame Plug-in for managing/executing multiple OpenSesame experiments.
License: LICENSE.md
Author: Bob Rosbag
Author-email: debian@bobrosbag.nl
Requires-Python: >=3.7
Classifier: License :: Other/Proprietary License
Classifier: Programming Language :: Python :: 3
Classifier: Programming Language :: Python :: 3.7
Classifier: Programming Language :: Python :: 3.8
Classifier: Programming Language :: Python :: 3.9
Classifier: Programming Language :: Python :: 3.10
Classifier: Programming Language :: Python :: 3.11
Classifier: Programming Language :: Python :: 3.12
Classifier: Programming Language :: Python :: 3.13
Project-URL: Homepage, https://github.com/dev-jam/opensesame-plugin-experiment_manager
Project-URL: Repository, https://github.com/dev-jam/opensesame-plugin-experiment_manager
